LitMath
